{
  "updated_at": "2026-07-13T19:17:24.138748Z",
  "sites": {
    "https://book.asahi.com/::::.module-latest-stories .module-list-articles__item::.module-list-articles__heading a::.module-list-articles__heading a::::.module-list-articles__category a, .module-list-articles__tags__item a": {
      "name": "好書好日",
      "url": "https://book.asahi.com/",
      "selector": "",
      "tag": "読書",
      "selector_attribute": "",
      "item_selector": ".module-latest-stories .module-list-articles__item",
      "title_selector": ".module-list-articles__heading a",
      "title_attribute": "",
      "link_selector": ".module-list-articles__heading a",
      "link_attribute": "",
      "summary_selector": "",
      "summary_attribute": "",
      "tags_selector": ".module-list-articles__category a, .module-list-articles__tags__item a",
      "tags_attribute": "",
      "hash": "fe5e44126f1f9154831a49b213ed665ce303606d997f6facbad0d506e55589bf",
      "last_checked_at": "2026-07-13T19:17:19.074024Z",
      "last_changed_at": "2026-07-13T02:08:27.985293Z"
    },
    "https://www.jrva.com/jrvanews/::::.news .card::h3.title::a.newslistlink::p.description::.tag-list li a": {
      "name": "JRVA NEWS",
      "url": "https://www.jrva.com/jrvanews/",
      "selector": "",
      "tag": "RVパーク",
      "selector_attribute": "",
      "item_selector": ".news .card",
      "title_selector": "h3.title",
      "title_attribute": "",
      "link_selector": "a.newslistlink",
      "link_attribute": "",
      "summary_selector": "p.description",
      "summary_attribute": "",
      "tags_selector": ".tag-list li a",
      "tags_attribute": "",
      "hash": "3ced1fdd88eacf59c50d23f662066e261edb1a0c64b0dbee1808096ce8c74340",
      "last_checked_at": "2026-07-13T19:17:20.314576Z",
      "last_changed_at": "2026-07-10T16:52:34.695103Z"
    },
    "https://president.jp/list/category/business::.article-list__mainTtl::.article-list__item::.article-list__mainTtl::.article-list__body a::.m-article__shoulder::": {
      "name": "PRESIDENT Online ビジネス",
      "url": "https://president.jp/list/category/business",
      "selector": ".article-list__mainTtl",
      "tag": "ビジネス",
      "selector_attribute": "",
      "item_selector": ".article-list__item",
      "title_selector": ".article-list__mainTtl",
      "title_attribute": "",
      "link_selector": ".article-list__body a",
      "link_attribute": "",
      "summary_selector": ".m-article__shoulder",
      "summary_attribute": "",
      "tags_selector": "",
      "tags_attribute": "",
      "hash": "e21c0b04e2646d8ab1f3ec92e8356b2b7eec8a9e8a224c8d3a6bbf1559d4951d",
      "last_checked_at": "2026-07-13T19:17:20.848850Z",
      "last_changed_at": "2026-07-13T02:08:29.628300Z"
    },
    "https://www.instagram.com/architects_need/reels/::meta[property='og:description']::::meta[property='og:title']::meta[property='og:url']::meta[name='description']::::content::content::content::content::": {
      "name": "Instagram architects_need Reels",
      "url": "https://www.instagram.com/architects_need/reels/",
      "selector": "meta[property='og:description']",
      "tag": "建築",
      "selector_attribute": "content",
      "item_selector": "",
      "title_selector": "meta[property='og:title']",
      "title_attribute": "content",
      "link_selector": "meta[property='og:url']",
      "link_attribute": "content",
      "summary_selector": "meta[name='description']",
      "summary_attribute": "content",
      "tags_selector": "",
      "tags_attribute": "",
      "hash": "5ec17494fec5e53688ad93dff0970a9ffea8065aa9f778edc47eda5290c53936",
      "last_checked_at": "2026-06-26T19:40:55.940656Z",
      "last_changed_at": "2026-06-26T19:40:55.940656Z"
    },
    "https://pharmacist.m3.com/column::::li.m3p-column-list__item::a.m3-heading1::a.m3-heading1::.m3p-column-list__description::.m3p-column-list__tagwarap a": {
      "name": "m3.com 薬剤師コラム",
      "url": "https://pharmacist.m3.com/column",
      "selector": "",
      "tag": "医療・薬",
      "selector_attribute": "",
      "item_selector": "li.m3p-column-list__item",
      "title_selector": "a.m3-heading1",
      "title_attribute": "",
      "link_selector": "a.m3-heading1",
      "link_attribute": "",
      "summary_selector": ".m3p-column-list__description",
      "summary_attribute": "",
      "tags_selector": ".m3p-column-list__tagwarap a",
      "tags_attribute": "",
      "hash": "ecfd2de6acbe38bd785a42463112d153c03c1870d24caf8894d0c39cbf6a45d4",
      "last_checked_at": "2026-07-13T19:17:22.512860Z",
      "last_changed_at": "2026-07-13T19:17:22.512860Z"
    }
  }
}
