{
  "updated_at": "2026-05-15T11:16:17.172820Z",
  "sites": {
    "https://book.asahi.com/::::.module-latest-stories .module-list-articles__item::.module-list-articles__heading a::.module-list-articles__heading a::::.module-list-articles__category a, .module-list-articles__tags__item a": {
      "name": "好書好日",
      "url": "https://book.asahi.com/",
      "selector": "",
      "tag": "読書",
      "selector_attribute": "",
      "item_selector": ".module-latest-stories .module-list-articles__item",
      "title_selector": ".module-list-articles__heading a",
      "title_attribute": "",
      "link_selector": ".module-list-articles__heading a",
      "link_attribute": "",
      "summary_selector": "",
      "summary_attribute": "",
      "tags_selector": ".module-list-articles__category a, .module-list-articles__tags__item a",
      "tags_attribute": "",
      "hash": "c8aa2796d40bd6b4c287499c8b6c96c66ebc432984fd69eaa12eb195bc33e2c7",
      "last_checked_at": "2026-05-15T11:16:15.248522Z",
      "last_changed_at": "2026-05-15T02:37:29.987733Z"
    },
    "https://www.jrva.com/jrvanews/::::.news .card::h3.title::a.newslistlink::p.description::.tag-list li a": {
      "name": "JRVA NEWS",
      "url": "https://www.jrva.com/jrvanews/",
      "selector": "",
      "tag": "RVパーク",
      "selector_attribute": "",
      "item_selector": ".news .card",
      "title_selector": "h3.title",
      "title_attribute": "",
      "link_selector": "a.newslistlink",
      "link_attribute": "",
      "summary_selector": "p.description",
      "summary_attribute": "",
      "tags_selector": ".tag-list li a",
      "tags_attribute": "",
      "hash": "011e2aeed77d14243af3e7538e82fe4865fadb4cc8cd8c03ef7816c8edd5a762",
      "last_checked_at": "2026-05-15T11:16:16.181795Z",
      "last_changed_at": ""
    },
    "https://www.instagram.com/architects_need/reels/::meta[property='og:description']::::meta[property='og:title']::meta[property='og:url']::meta[name='description']::::content::content::content::content::": {
      "name": "Instagram architects_need Reels",
      "url": "https://www.instagram.com/architects_need/reels/",
      "selector": "meta[property='og:description']",
      "tag": "建築",
      "selector_attribute": "content",
      "item_selector": "",
      "title_selector": "meta[property='og:title']",
      "title_attribute": "content",
      "link_selector": "meta[property='og:url']",
      "link_attribute": "content",
      "summary_selector": "meta[name='description']",
      "summary_attribute": "content",
      "tags_selector": "",
      "tags_attribute": "",
      "hash": "88137893ce094defc0d5cf3b6abc30bc832f647e221974088faf9bd28046246d",
      "last_checked_at": "2026-05-15T11:16:16.739419Z",
      "last_changed_at": "2026-05-14T22:05:41.204425Z"
    }
  }
}
